aws_gate/__init__.py
aws_gate/bootstrap.py
aws_gate/cli.py
aws_gate/config.py
aws_gate/constants.py
aws_gate/decorators.py
aws_gate/exceptions.py
aws_gate/exec.py
aws_gate/list.py
aws_gate/query.py
aws_gate/session.py
aws_gate/session_common.py
aws_gate/ssh.py
aws_gate/ssh_common.py
aws_gate/ssh_config.py
aws_gate/ssh_proxy.py
aws_gate/utils.py
aws_gate-0.11.3.data/scripts/aws-gate
tests/__init__.py
tests/run.py
tests/unit/__init__.py
tests/unit/conftest.py
tests/unit/test_bootstrap.py
tests/unit/test_cli.py
tests/unit/test_config.py
tests/unit/test_decorators.py
tests/unit/test_exec.py
tests/unit/test_list.py
tests/unit/test_query.py
tests/unit/test_session.py
tests/unit/test_ssh.py
tests/unit/test_ssh_common.py
tests/unit/test_ssh_config.py
tests/unit/test_ssh_proxy.py
tests/unit/test_utils.py
aws_gate-0.11.3.dist-info/LICENSE.md
aws_gate-0.11.3.dist-info/METADATA
aws_gate-0.11.3.dist-info/WHEEL
aws_gate-0.11.3.dist-info/top_level.txt
aws_gate-0.11.3.dist-info/RECORD
