Metadata-Version: 2.1
Name: aws-gate
Version: 0.11.3
Summary: aws-gate - AWS SSM Session Manager client CLI
Home-page: https://github.com/xen0l/aws-gate
Author: Adam Stevko
Author-email: adam.stevko@gmail.com
Project-URL: Bug Tracker, https://github.com/xen0l/aws-gate/issues
Project-URL: Source Code, https://github.com/xen0l/aws-gate
Classifier: Programming Language :: Python :: 3
Classifier: License :: OSI Approved :: BSD License
Classifier: Operating System :: OS Independent
Classifier: Topic :: System :: Systems Administration
License-File: LICENSE.md
Requires-Dist: boto3 (~=1.26.151)
Requires-Dist: cryptography (==39.0.2)
Requires-Dist: marshmallow (==3.19.0)
Requires-Dist: packaging (==23.0)
Requires-Dist: PyYAML (<6.1,>=5.1)
Requires-Dist: requests (==2.28.2)
Requires-Dist: unix-ar (==0.2.1)
Requires-Dist: wrapt (==1.15.0)
Provides-Extra: tests
Requires-Dist: attrs (==22.2.0) ; extra == 'tests'
Requires-Dist: bandit (==1.7.5) ; extra == 'tests'
Requires-Dist: black (==23.1.0) ; extra == 'tests'
Requires-Dist: dlint (==0.12.0) ; extra == 'tests'
Requires-Dist: flake8 (==4.0.1) ; extra == 'tests'
Requires-Dist: flake8-bandit (==2.1.2) ; extra == 'tests'
Requires-Dist: flake8-bugbear (==23.2.13) ; extra == 'tests'
Requires-Dist: hypothesis (==6.68.2) ; extra == 'tests'
Requires-Dist: invoke (==2.0.0) ; extra == 'tests'
Requires-Dist: placebo (==0.10.0) ; extra == 'tests'
Requires-Dist: pre-commit (==2.20.0) ; extra == 'tests'
Requires-Dist: pylint (==2.17.0) ; extra == 'tests'
Requires-Dist: pytest (==7.2.2) ; extra == 'tests'
Requires-Dist: pytest-black (==0.3.12) ; extra == 'tests'
Requires-Dist: pytest-cov (==4.0.0) ; extra == 'tests'
Requires-Dist: pytest-datadir (==1.4.1) ; extra == 'tests'
Requires-Dist: pytest-mock (==3.10.0) ; extra == 'tests'
Requires-Dist: pytest-pylint (==0.18.0) ; extra == 'tests'
